[
	{
		"id":"0601B",
		"shopname":"流行发色和发型",
		"items":[
			{
				"id":"1",
				"majorname":"",
				"itemname":"今日头条=流行发色",
				"author": "",
				"resUrl":"http://www.toutiao.com/search/?keyword=流行发色",
				"itemstatus": "regular",
				"remarks":""
			},
			{
				"id":"2",
				"majorname":"",
				"itemname":"发型站",
				"author": "",
				"resUrl":"http://www.faxingzhan.com/fxsj/ranfa/",
				"itemstatus": "regular",
				"remarks":""
			},
                        {
				"id":"3",
				"majorname":"",
				"itemname":"2016最流行发色",
				"author": "",
				"resUrl":"http://mp.weixin.qq.com/s?__biz=MzA4NTMyMDYyOA%3D%3D&idx=5&mid=2651408958&sn=ee3a26034ed415299292f2ed826e7e1d",
				"itemstatus": "regular",
				"remarks":""
			},
                        {
				"id":"4",
				"majorname":"",
				"itemname":"新浪时尚",
				"author": "",
				"resUrl":"http://fashion.sina.com.cn/b/ha/2016-03-18/0706/doc-ifxqnski7682293.shtml",
				"itemstatus": "regular",
				"remarks":""
			},
                        {
				"id":"5",
				"majorname":"",
				"itemname":"新华网之流行发色",
				"author": "",
				"resUrl":"http://news.xinhuanet.com/fashion/2016-03/22/c_128810810.htm",
				"itemstatus": "regular",
				"remarks":""
			},
                        {
				"id":"6",
				"majorname":"",
				"itemname":"夏天马尾这么扎，瞬间变女神！",
				"author": "",
				"resUrl":"http://toutiao.com/a6294948777837641985/",
				"itemstatus": "regular",
				"remarks":""
			},
                        {
				"id":"7",
				"majorname":"",
				"itemname":"s型刘海卷发",
				"author": "",
				"resUrl":"http://toutiao.com/a6315186325147484418/",
				"itemstatus": "regular",
				"remarks":""
			},
                        {
				"id":"8",
				"majorname":"",
				"itemname":"还在痴迷于丸子头？现在已是辫子的天下啦",
				"author": "",
				"resUrl":"http://toutiao.com/a6315008886722003457/",
				"itemstatus": "regular",
				"remarks":""
			},
                        {
				"id":"9",
				"majorname":"",
				"itemname":"2款简单速成扎法教程步骤图",
				"author": "",
				"resUrl":"http://www.mnw.cn/news/consumer/1290761.html?tt_group_id=6311884215047274754",
				"itemstatus": "regular",
				"remarks":""
			},
                        {
				"id":"10",
				"majorname":"",
				"itemname":"欧美复古编发盘发教程",
				"author": "",
				"resUrl":"http://toutiao.com/a6311874176488440065/",
				"itemstatus": "regular",
				"remarks":""
			},
                        {
				"id":"11",
				"majorname":"",
				"itemname":"学会这几款半扎发，你也能像郑爽一样美！",
				"author": "",
				"resUrl":"http://toutiao.com/a6314986188277023234/",
				"itemstatus": "regular",
				"remarks":""
			},
                        {
				"id":"12",
				"majorname":"",
				"itemname":"12款甜美look承包你一整年的造型",
				"author": "",
				"resUrl":"http://toutiao.com/a6314480040478245121/",
				"itemstatus": "regular",
				"remarks":""
			},
                        {
				"id":"13",
				"majorname":"",
				"itemname":"8款流行短发照着剪美出新高度",
				"author": "",
				"resUrl":"http://toutiao.com/a6314532604977201410/",
				"itemstatus": "regular",
				"remarks":""
			},
                        {
				"id":"14",
				"majorname":"",
				"itemname":"这些扎发百搭超撩人",
				"author": "",
				"resUrl":"http://toutiao.com/a6312546502120341762/",
				"itemstatus": "regular",
				"remarks":""
			},
                        {
				"id":"15",
				"majorname":"",
				"itemname":"选择适合的发型，展现出完美脸型",
				"author": "",
				"resUrl":"http://toutiao.com/a6315332952684757249/",
				"itemstatus": "regular",
				"remarks":""
			},
                        {
				"id":"16",
				"majorname":"",
				"itemname":"2016流行发型揭秘，韩国妹子都在留这些款！",
				"author": "",
				"resUrl":"http://www.chinadaily.com.cn/interface/toutiaonew/1020961/2016-06-16/cd_25731011.html?tt_group_id=6296341130934239489",
				"itemstatus": "regular",
				"remarks":""
			},
                        {
				"id":"17",
				"majorname":"",
				"itemname":"今年流行的卷度发色",
				"author": "",
				"resUrl":"http://toutiao.com/a6285115672734204161/",
				"itemstatus": "regular",
				"remarks":""
			},
                        {
				"id":"18",
				"majorname":"",
				"itemname":"好发型不如一款好发色!最吸睛流行发色安利给你",
				"author": "",
				"resUrl":"http://m2.people.cn/r/MV80XzY4MjAyMTZfMTc2M18xNDYyNzU5NjU3?tt_group_id=6281749581610008834",
				"itemstatus": "regular",
				"remarks":""
			},
                        {
				"id":"19",
				"majorname":"",
				"itemname":"今夏最in发型：尽显法式优雅美丽",
				"author": "",
				"resUrl":"http://toutiao.com/a6303781282090467585/",
				"itemstatus": "regular",
				"remarks":""
			},
                        {
				"id":"20",
				"majorname":"",
				"itemname":"学韩国女生流行发型",
				"author": "",
				"resUrl":"http://toutiao.com/a6303311876035084545/",
				"itemstatus": "regular",
				"remarks":""
			}
		        ]
	}
]