[
	{
		"id":"0401C",
		"shopname":"PS软件下载",
		"items":[
			{
				"id":"1",
				"majorname":"",
				"itemname":"Adobe PhotoShop CS6",
				"author": "",
				"resUrl":"http://rj.baidu.com/soft/detail/23675.html?ald",
				"itemstatus": "regular",
				"remarks":""
			},
			{
				"id":"2",
				"majorname":"",
				"itemname":"Adobe Photoshop CS4(photoshop cs4下载)11.0.1 Extended ps中文版",
				"author": "",
				"resUrl":"http://www.xiazaiba.com/html/175.html",
				"itemstatus": "regular",
				"remarks":""
			},
                       {
				"id":"3",
				"majorname":"",
				"itemname":"Adobe Photoshop CS3 Extended(photoshopcs3中文版)10.0.0.0简体中文免费版",
				"author": "",
				"resUrl":"http://www.xiazaiba.com/html/490.html",
				"itemstatus": "regular",
				"remarks":""
			},
                       {
				"id":"4",
				"majorname":"",
				"itemname":"Adobe Photoshop Lightroom 6.0(专业摄影师图像处理软件)中文版",
				"author": "",
				"resUrl":"http://www.xiazaiba.com/html/1164.html",
				"itemstatus": "regular",
				"remarks":""
			},
                       {
				"id":"5",
				"majorname":"",
				"itemname":"Adobe Photoshop CS5 Extended 12.0.3.0官方中文版",
				"author": "",
				"resUrl":"http://www.xiazaiba.com/html/1687.html",
				"itemstatus": "regular",
				"remarks":""
			},
                       {
				"id":"6",
				"majorname":"",
				"itemname":"Adobe Photoshop7.0中文版",
				"author": "",
				"resUrl":"http://www.xiazaiba.com/html/2789.html",
				"itemstatus": "regular",
				"remarks":""
			},
                       {
				"id":"7",
				"majorname":"",
				"itemname":"PhotoshopRecovery V2.0 (恢复Photoshop程序)",
				"author": "",
				"resUrl":"http://www.xiazaiba.com/html/175.html",
				"itemstatus": "regular",
				"remarks":""
			},
                        {
				"id":"8",
				"majorname":"",
				"itemname":"Adobe Photoshop Lightroom for Mac 6.0官方中文版(Lightroom苹果版)",
				"author": "",
				"resUrl":"http://www.xiazaiba.com/html/4360.html",
				"itemstatus": "regular",
				"remarks":""
			},
                        {
				"id":"9",
				"majorname":"",
				"itemname":"Photoshop Speedup V3.0(提高Photoshop启动速度)",
				"author": "",
				"resUrl":"http://www.xiazaiba.com/html/6673.html",
				"itemstatus": "regular",
				"remarks":""
			},
                        {
				"id":"10",
				"majorname":"",
				"itemname":"Adobe Photoshop CS6 13.0.1 Extended 官方中文版",
				"author": "",
				"resUrl":"http://www.xiazaiba.com/html/6764.html",
				"itemstatus": "regular",
				"remarks":""
			},
                        {
				"id":"11",
				"majorname":"",
				"itemname":"Adobe Photoshop CS2官方版(photoshop cs2中文版下载)",
				"author": "",
				"resUrl":"http://www.xiazaiba.com/html/7735.html",
				"itemstatus": "regular",
				"remarks":""
			},
                        {
				"id":"12",
				"majorname":"",
				"itemname":"Adobe Photoshop CC 2015 64位版(photoshop下载)16.0.0.88中文版",
				"author": "",
				"resUrl":"http://www.xiazaiba.com/html/25998.html",
				"itemstatus": "regular",
				"remarks":""
			},
                        {
				"id":"13",
				"majorname":"",
				"itemname":"Adobe Photoshop CC 2015(ps cc下载)16.0.0.88官方中文版",
				"author": "",
				"resUrl":"http://www.xiazaiba.com/html/25991.html",
				"itemstatus": "regular",
				"remarks":""
			},
                        {
				"id":"14",
				"majorname":"",
				"itemname":"Adobe Photoshop CC for Mac 2015官方中文版下载",
				"author": "",
				"resUrl":"http://www.xiazaiba.com/html/30146.html",
				"itemstatus": "regular",
				"remarks":""
			},
                        {
				"id":"15",
				"majorname":"",
				"itemname":"Adobe Photoshop CS6 x64位版本（ps下载中文版） 官方简体中文版",
				"author": "",
				"resUrl":"http://www.xiazaiba.com/html/23805.html",
				"itemstatus": "regular",
				"remarks":""
			},
                        {
				"id":"16",
				"majorname":"",
				"itemname":"Adobe Photoshop CC 64位中文正式版(制作图片软件 ps图片处理软件)",
				"author": "",
				"resUrl":"http://www.xiazaiba.com/html/24956.html",
				"itemstatus": "regular",
				"remarks":""
			},
                       {
				"id":"17",
				"majorname":"",
				"itemname":"Artweaver Plus(精简版Photoshop)V5.0.7官方中文版",
				"author": "",
				"resUrl":"http://www.xiazaiba.com/html/2323.html",
				"itemstatus": "regular",
				"remarks":""
			},
                       {
				"id":"18",
				"majorname":"",
				"itemname":"photoshop7.0中文官方版",
				"author": "",
				"resUrl":"http://www.downza.cn/soft/192030.html",
				"itemstatus": "regular",
				"remarks":""
			},
                       {
				"id":"19",
				"majorname":"",
				"itemname":"photoshop7.0中文官方免费版",
				"author": "",
				"resUrl":"http://www.downza.cn/soft/191630.html",
				"itemstatus": "regular",
				"remarks":""
			},
                       {
				"id":"20",
				"majorname":"",
				"itemname":"photoshop中文版下载V13.1.3",
				"author": "",
				"resUrl":"http://www.downza.cn/soft/27536.html",
				"itemstatus": "regular",
				"remarks":""
			}
		]
	}
]